AsyncLibrary/__init__.py
AsyncLibrary/robot_async.py
robotframework_async-1.0.4.dist-info/LICENSE.txt
robotframework_async-1.0.4.dist-info/METADATA
robotframework_async-1.0.4.dist-info/WHEEL
robotframework_async-1.0.4.dist-info/top_level.txt
robotframework_async-1.0.4.dist-info/RECORD
