Metadata-Version: 2.1
Name: robotframework-async
Version: 1.0.4
Summary: Generic Robot Framework library for asynchronous keyword execution
Home-page: https://github.com/Chetic/robotframework-async
Author: Fredrik Reveny
Author-email: chetic@gmail.com
License: MIT
Download-URL: https://github.com/Chetic/robotframework-async
Keywords: async,robotframework
Platform: UNKNOWN
Classifier: Programming Language :: Python :: 2
Classifier: Programming Language :: Python :: 3
Classifier: Development Status :: 4 - Beta
Classifier: Environment :: Other Environment
Classifier: Intended Audience :: Developers
Classifier: Operating System :: OS Independent
Classifier: Topic :: Software Development :: Libraries :: Python Modules
Requires-Dist: robotframework (>=2.8.6)
